async_pcloud/__init__.py
async_pcloud/api.py
async_pcloud/exceptions.py
async_pcloud/utils.py
async_pcloud/validate.py
async_pcloud-0.3.0.dist-info/licenses/LICENSE
async_pcloud-0.3.0.dist-info/METADATA
async_pcloud-0.3.0.dist-info/WHEEL
async_pcloud-0.3.0.dist-info/top_level.txt
async_pcloud-0.3.0.dist-info/RECORD
