Metadata-Version: 2.4
Name: async_pcloud
Version: 0.3.0
Summary: Async python API client for PCloud
Author: Noob
License-Expression: MIT
Project-URL: Homepage, https://github.com/Noob-Lol/async_pcloud
Project-URL: Issues, https://github.com/Noob-Lol/async_pcloud/issues
Keywords: Python,pCloud,async,REST
Classifier: Programming Language :: Python :: 3
Classifier: Operating System :: OS Independent
Classifier: Topic :: Software Development :: Libraries :: Python Modules
Requires-Python: >=3.9
License-File: LICENSE
Requires-Dist: aiohttp<4,>=3.9
Requires-Dist: anyio>=3.7
Provides-Extra: test
Requires-Dist: pytest>=8.3.5; extra == "test"
Requires-Dist: flake8>=7.1.1; extra == "test"
Requires-Dist: pytest-asyncio>=1.0.0; extra == "test"
Dynamic: license-file
